{
  "timestamp": "2026-03-18T06:31:53.637Z",
  "wallet": "0x410a41682158DF340AF54cB3F706D144ee3a7CA8",
  "balances": [
    {
      "network": "Ethereum Sepolia",
      "token": "ETH",
      "balance": 0.9421199866938285
    },
    {
      "network": "Base Sepolia",
      "token": "ETH",
      "balance": 0.009977166801952191
    },
    {
      "network": "Arbitrum Sepolia",
      "token": "ETH",
      "balance": 0.009880019011602
    },
    {
      "network": "Optimism Sepolia",
      "token": "ETH",
      "balance": 0.00979545132094224
    },
    {
      "network": "MegaETH Testnet",
      "token": "ETH",
      "balance": 0
    },
    {
      "network": "Monad Testnet",
      "token": "MON",
      "balance": 0
    },
    {
      "network": "Pharos Testnet",
      "token": "PHRS",
      "balance": 0,
      "error": "timeout"
    },
    {
      "network": "Polygon Amoy",
      "token": "POL",
      "balance": 0
    },
    {
      "network": "Lens Sepolia",
      "token": "GRASS",
      "balance": 0
    },
    {
      "network": "ZKsync Sepolia",
      "token": "ETH",
      "balance": 0
    },
    {
      "network": "Rise Testnet",
      "token": "ETH",
      "balance": 0
    },
    {
      "network": "Abstract Testnet",
      "token": "ETH",
      "balance": 0
    },
    {
      "network": "Berachain Bepolia",
      "token": "BERA",
      "balance": 0
    },
    {
      "network": "Scroll Sepolia",
      "token": "ETH",
      "balance": 0.009958101029674087
    },
    {
      "network": "Linea Sepolia",
      "token": "ETH",
      "balance": 0.009923024849408
    },
    {
      "network": "Fluent Testnet",
      "token": "ETH",
      "balance": 0
    }
  ],
  "totalNetworks": 16,
  "networksWithBalance": 6
}